matchmakereft/__init__.py
matchmakereft/core/FR2MM.m
matchmakereft/core/check_linear_dependence.wl
matchmakereft/core/compute_rge_model_to_eft.wl
matchmakereft/core/compute_wilson_coefficients.wl
matchmakereft/core/create_MM_model.wl
matchmakereft/core/generaldefs_skeleton.h
matchmakereft/core/getmathpath.wl
matchmakereft/core/matcher.m
matchmakereft/core/matchmakereft.m
matchmakereft/core/my.sty
matchmakereft/core/procedures.h
matchmakereft/core/skeleton_frm_reunite
matchmakereft/core/skeleton_parallel_new.frm
matchmakereft/core/test.wl
matchmakereft/data/models.tar.gz
matchmakereft/data/test_suite.tar.gz
matchmakereft/docs/UpdateNotes.txt
matchmakereft/docs/manual.pdf
matchmakereft/libs/MatchMaker.py
matchmakereft/libs/__init__.py
matchmakereft/libs/file.py
matchmakereft/libs/functions.py
matchmakereft/libs/generate_form.py
matchmakereft/libs/init_mm.py
matchmakereft/libs/match_model.py
matchmakereft/libs/mm_offline.py
matchmakereft/libs/run_all.py
matchmakereft/libs/run_form.py
matchmakereft/libs/run_qgraf.py
matchmakereft/libs/test_suite.py
matchmakereft-1.1.3.dist-info/LICENSE
matchmakereft-1.1.3.dist-info/METADATA
matchmakereft-1.1.3.dist-info/WHEEL
matchmakereft-1.1.3.dist-info/entry_points.txt
matchmakereft-1.1.3.dist-info/top_level.txt
matchmakereft-1.1.3.dist-info/RECORD
