Metadata-Version: 2.1
Name: matchmakereft
Version: 1.1.3
Summary: Automated matching of general models onto general effective field theories
Home-page: https://ftae.ugr.es/matchmakereft/
Author: Adrian Carmona, Achilleas Lazopoulos, Pablo Olgoso, Jose Santiago
Author-email: adrian@ugr.es, lazopoulos@itp.phys.ethz.ch, pablolgoso@ugr.es, jsantiago@ugr.es
License: GNU General Public License GPLv3
Classifier: Programming Language :: Python :: 3
Classifier: Operating System :: OS Independent
License-File: LICENSE
Requires-Dist: colorama
Requires-Dist: requests
Requires-Dist: setuptools
Requires-Dist: tqdm (>=4.62.3)
Requires-Dist: version-comparison
Requires-Dist: yolk3k
